<?xml version = '1.0' encoding = 'UTF-8'?>
<Diagram class="oracle.dbtools.crest.swingui.relational.DPVRelational" name="USIM" id="7880188E-F4D3-0F70-59E9-6B05650CAB0E">
<createdBy>Adi</createdBy>
<modifiedBy>Adi</modifiedBy>
<createdTime>2023-04-20 22:42:14 UTC</createdTime>
<autoRoute>false</autoRoute>
<boxInbox>true</boxInbox>
<showLegend>false</showLegend>
<showLabels>false</showLabels>
<showRelAttributes>false</showRelAttributes>
<gridEnabled>false</gridEnabled>
<showGrid>false</showGrid>
<diagramColor>-1</diagramColor>
<display>false</display>
<notation>1</notation>
<objectViews>
<OView class="oracle.dbtools.crest.swingui.relational.TVTable" oid="33726369-13BE-C07C-F21D-59C1A6816E82" otype="Table" vid="082D233F-E598-3903-9034-99B24D7E0AF1">
<hideElementsInCurrentOnly>false</hideElementsInCurrentOnly>
<bounds x="20" y="163" width="209" height="110"/>
</OView>
<OView class="oracle.dbtools.crest.swingui.relational.TVTable" oid="87E7E78E-8508-C00B-AF84-5D7D0C0EAB93" otype="Table" vid="CBC309AC-CD30-39E2-7269-A86552C6EB2A">
<hideElementsInCurrentOnly>false</hideElementsInCurrentOnly>
<bounds x="781" y="484" width="209" height="107"/>
</OView>
<OView class="oracle.dbtools.crest.swingui.relational.TVTable" oid="8A925212-FBD7-C71F-67F1-445E33106C0D" otype="Table" vid="99E20CAA-31CC-5104-745A-51E1FC91F8F6">
<hideElementsInCurrentOnly>false</hideElementsInCurrentOnly>
<bounds x="19" y="508" width="210" height="81"/>
</OView>
<OView class="oracle.dbtools.crest.swingui.relational.TVTable" oid="A1DD6960-9A69-44A2-B7B3-E6324646C526" otype="Table" vid="626DC274-7FF2-CAE6-AA44-8A3242EC5A8D">
<hideElementsInCurrentOnly>false</hideElementsInCurrentOnly>
<bounds x="20" y="402" width="210" height="88"/>
</OView>
<OView class="oracle.dbtools.crest.swingui.relational.TVTable" oid="B0EDB40C-9524-AE53-A7A1-D9EFD9661B28" otype="Table" vid="152F7204-6424-506B-5AF6-37B3E6FECBC3">
<hideElementsInCurrentOnly>false</hideElementsInCurrentOnly>
<bounds x="408" y="501" width="207" height="116"/>
</OView>
</objectViews>
<connectors>
<Connector class="oracle.dbtools.crest.swingui.relational.TVFKRelation" oid="101FD80E-5291-A36E-EF15-65D113D8F2AC" otype="FKIndexAssociation" vid_source="CBC309AC-CD30-39E2-7269-A86552C6EB2A" vid_target="152F7204-6424-506B-5AF6-37B3E6FECBC3">
<hideElementsInCurrentOnly>false</hideElementsInCurrentOnly>
<backgroundColor>-16777216</backgroundColor>
<lineWidth>1</lineWidth>
<points>
<point x="781" y="546"/>
<point x="615" y="542"/>
</points>
</Connector>
</connectors>
</Diagram>